pypopipette_game/backend.py
pypopipette_game/frontend.py
pypopipette_game-0.0.2.dist-info/LICENSE
pypopipette_game-0.0.2.dist-info/METADATA
pypopipette_game-0.0.2.dist-info/WHEEL
pypopipette_game-0.0.2.dist-info/RECORD
