Metadata-Version: 2.1
Name: pypopipette_game
Version: 0.0.2
Summary: My take on the Dots and Squares game (Pipopipette in French).
License: LICENCE
Author: David GERARD
Author-email: david.gerard.23@ucl.ac.uk
Requires-Python: >=3.10,<4.0
Classifier: License :: Other/Proprietary License
Classifier: Programming Language :: Python :: 3
Classifier: Programming Language :: Python :: 3.10
Classifier: Programming Language :: Python :: 3.11
Classifier: Programming Language :: Python :: 3.12
Classifier: Programming Language :: Python :: 3.13
Requires-Dist: numpy (>=2.1.3,<3.0.0)
